connectlife/__init__.py
connectlife/api.py
connectlife/appliance.py
connectlife/dump.py
connectlife/tests/__init__.py
connectlife/tests/test_appliance.py
connectlife-0.5.4.dist-info/METADATA
connectlife-0.5.4.dist-info/WHEEL
connectlife-0.5.4.dist-info/licenses/LICENSE
connectlife-0.5.4.dist-info/RECORD
