Metadata-Version: 2.4
Name: connectlife
Version: 0.5.4
Summary: A Python library for communicating with the ConnectLife API
Project-URL: Homepage, https://github.com/oyvindwe/connectlife
Project-URL: Issues, https://github.com/oyvindwe/connectlife/issues
Author-email: Øyvind Matheson Wergeland <oyvind@wergeland.org>
License-File: LICENSE
Classifier: License :: OSI Approved :: GNU General Public License v3 (GPLv3)
Classifier: Operating System :: OS Independent
Classifier: Programming Language :: Python :: 3
Requires-Python: >=3.11
Requires-Dist: aiohttp>=3.9.5
